{
	"addons": {
		"testingthemeonMV3@themes": {
			"updates": [{
				"version": "1.0",
				"update_link": "https://ioanarusiczki.github.io/theme1.xpi"
			}]
		},
		"testingthemeonMV3@themes": {
			"updates": [{
				"version": "2.0",
				"update_link": "https://ioanarusiczki.github.io/theme2.xpi"
			}]
		},
		"testingthemeonMV3@themes": {
			"updates": [{
				"version": "3.0",
				"update_link": "https://ioanarusiczki.github.io/theme3.xpi"
			}]
		},
		"testingthemeonMV3@themes": {
			"updates": [{
				"version": "4.0",
				"update_link": "https://ioanarusiczki.github.io/theme4.xpi"
			}]
		},
		"MV2testlaMV2@test": {
			"updates": [{
				"version": "1.0",
				"update_link": "https://ioanarusiczki.github.io/MV2.xpi"
			}]
		},

		"MV2testlaMV2@test": {
			"updates": [{
				"version": "2.0.1",
				"update_link": "https://ioanarusiczki.github.io/MV3.xpi"
			}]

		},
		
		"copyplaintext2@eros.man": {
			"updates": [{
				"version": "1.17",
				"update_link": "https://ioanarusiczki.github.io/plaintext1.xpi"
			}]

		},
			"copyplaintext2@eros.man": {
			"updates": [{
				"version": "1.20",
				"update_link": "https://ioanarusiczki.github.io/plaintext2.xpi"
			}]

		},
			"copyplaintext4@eros.man": {
			"updates": [{
				"version": "1.18",
				"update_link": "https://ioanarusiczki.github.io/test18.xpi"
			}]

		},
		
				"copyplaintext4@eros.man": {
			"updates": [{
				"version": "1.19",
				"update_link": "https://ioanarusiczki.github.io/test19.xpi"
			}]

		},
		
			"unlistedtest@test.com": {
			"updates": [{
				"version": "2.2.0",
				"update_link": "https://ioanarusiczki.github.io/beta1.xpi"
			}]

		},
		
			"unlistedtest@test.com": {
			"updates": [{
				"version": "2.2.2",
				"update_link": "https://ioanarusiczki.github.io/beta2.xpi"
			}]

		},
		
		"unlistedtest1@test.com": {
			"updates": [{
				"version": "2.2.3",
				"update_link": "https://ioanarusiczki.github.io/mixedversions223.xpi"
			}]

		},
		
			"unlistedtest1@test.com": {
			"updates": [{
				"version": "2.2.4",
				"update_link": "https://ioanarusiczki.github.io/mixedversions224.xpi"
			}]

		},
		
		"{53f4ce58-b1b2-4b45-92c5-da87bacf1c12}": {
			"updates": [{
				"version": "1.0",
				"update_link": "https://ioanarusiczki.github.io/version1.xpi"
			},
			{
				"version": "2.0",
				"update_link": "https://ioanarusiczki.github.io/version2.xpi",
				"browser_specific_settings": {
					"gecko": {
						"strict_min_version": "109.0a1"
					}
				}
			}]

		}

	}
}